netbound/__init__.py
netbound/constants.py
netbound/packet.py
netbound/app/__init__.py
netbound/app/game.py
netbound/app/logging_adapter.py
netbound/app/protocol.py
netbound/app/server.py
netbound/packet/__init__.py
netbound/packet/serializer.py
netbound/state/__init__.py
netbound/state/base.py
netbound-0.1.21.dist-info/METADATA
netbound-0.1.21.dist-info/WHEEL
netbound-0.1.21.dist-info/top_level.txt
netbound-0.1.21.dist-info/RECORD
