Metadata-Version: 2.1
Name: netbound
Version: 0.1.21
Home-page: https://github.com/tristanbatchler/netbound
Author: Tristan Batchler
License: MIT
Requires-Dist: aiosqlite ==0.20.0
Requires-Dist: alembic ==1.13.1
Requires-Dist: annotated-types ==0.6.0
Requires-Dist: bcrypt ==4.1.2
Requires-Dist: cffi ==1.16.0
Requires-Dist: cryptography ==42.0.5
Requires-Dist: greenlet ==3.0.3
Requires-Dist: Mako ==1.3.2
Requires-Dist: MarkupSafe ==2.1.5
Requires-Dist: msgpack ==1.0.8
Requires-Dist: msgpack-types ==0.2.0
Requires-Dist: mypy ==1.9.0
Requires-Dist: mypy-extensions ==1.0.0
Requires-Dist: pycparser ==2.21
Requires-Dist: pydantic ==2.6.4
Requires-Dist: pydantic-core ==2.16.3
Requires-Dist: SQLAlchemy ==2.0.28
Requires-Dist: typing-extensions ==4.10.0
Requires-Dist: websockets ==12.0
